{"song_id": "1182279059623923753", "download": "https://cdn.discordapp.com/attachments/1128313332273782784/1182279059623923753/chirp.mp4?ex=65841e2d&amp", "lyrics": "Yesterday\nAll my troubles seemed so far away\nNow it looks as though they're here to stay\nOh, I believe in yesterday\n\nSuddenly\nI'm not half the man I used to be\nThere's a shadow hanging over me\nOh, yesterday came suddenly", "style": ["pop</span><span>, Elton John"], "essentia_features": {"lowlevel.average_loudness": 0.9674286246299744, "lowlevel.barkbands_crest.mean": 15.97634506225586, "lowlevel.barkbands_crest.stdev": 5.752298355102539, "lowlevel.barkbands_flatness_db.mean": 0.2090950608253479, "lowlevel.barkbands_flatness_db.stdev": 0.082265704870224, "lowlevel.barkbands_kurtosis.mean": 36.99382019042969, "lowlevel.barkbands_kurtosis.stdev": 58.22403335571289, "lowlevel.barkbands_skewness.mean": 4.481743335723877, "lowlevel.barkbands_skewness.stdev": 3.4235877990722656, "lowlevel.barkbands_spread.mean": 22.841712951660156, "lowlevel.barkbands_spread.stdev": 23.693002700805664, "lowlevel.dissonance.mean": 0.45478880405426025, "lowlevel.dissonance.stdev": 0.032089218497276306, "lowlevel.dynamic_complexity": 2.6530938148498535, "lowlevel.erbbands_crest.mean": 9.188732147216797, "lowlevel.erbbands_crest.stdev": 3.8948585987091064, "lowlevel.erbbands_flatness_db.mean": 0.11220932006835938, "lowlevel.erbbands_flatness_db.stdev": 0.032955847680568695, "lowlevel.erbbands_kurtosis.mean": 0.5401411056518555, "lowlevel.erbbands_kurtosis.stdev": 2.138228178024292, "lowlevel.erbbands_skewness.mean": 0.5951600670814514, "lowlevel.erbbands_skewness.stdev": 0.9373478889465332, "lowlevel.erbbands_spread.mean": 77.26475524902344, "lowlevel.erbbands_spread.stdev": 39.09077072143555, "lowlevel.hfc.mean": 24.746692657470703, "lowlevel.hfc.stdev": 29.664703369140625, "lowlevel.loudness_ebu128.integrated": -18.792678833007812, "lowlevel.loudness_ebu128.loudness_range": 0.92913818359375, "lowlevel.loudness_ebu128.momentary.mean": -19.317825317382812, "lowlevel.loudness_ebu128.momentary.stdev": 2.3211708068847656, "lowlevel.loudness_ebu128.short_term.mean": -18.791372299194336, "lowlevel.loudness_ebu128.short_term.stdev": 0.29611635208129883, "lowlevel.melbands_crest.mean": 20.23120880126953, "lowlevel.melbands_crest.stdev": 6.4865922927856445, "lowlevel.melbands_flatness_db.mean": 0.30770593881607056, "lowlevel.melbands_flatness_db.stdev": 0.10752537101507187, "lowlevel.melbands_kurtosis.mean": 123.89195251464844, "lowlevel.melbands_kurtosis.stdev": 163.31504821777344, "lowlevel.melbands_skewness.mean": 7.2854108810424805, "lowlevel.melbands_skewness.stdev": 4.564119815826416, "lowlevel.melbands_spread.mean": 11.174798965454102, "lowlevel.melbands_spread.stdev": 14.611709594726562, "lowlevel.pitch_salience.mean": 0.4190685749053955, "lowlevel.pitch_salience.stdev": 0.16640274226665497, "lowlevel.silence_rate_20dB.mean": 0.9971671104431152, "lowlevel.silence_rate_20dB.stdev": 0.05314938351511955, "lowlevel.silence_rate_30dB.mean": 0.8111425638198853, "lowlevel.silence_rate_30dB.stdev": 0.3913940191268921, "lowlevel.silence_rate_60dB.mean": 0.06704438477754593, "lowlevel.silence_rate_60dB.stdev": 0.2500978410243988, "lowlevel.spectral_centroid.mean": 1034.4124755859375, "lowlevel.spectral_centroid.stdev": 716.7040405273438, "lowlevel.spectral_complexity.mean": 8.94711971282959, "lowlevel.spectral_complexity.stdev": 6.78532075881958, "lowlevel.spectral_decrease.mean": -1.6735254959598933e-08, "lowlevel.spectral_decrease.stdev": 1.8516882249741684e-08, "lowlevel.spectral_energy.mean": 0.06540729105472565, "lowlevel.spectral_energy.stdev": 0.070599265396595, "lowlevel.spectral_energyband_high.mean": 0.0015184151707217097, "lowlevel.spectral_energyband_high.stdev": 0.0026763277128338814, "lowlevel.spectral_energyband_low.mean": 0.05323053151369095, "lowlevel.spectral_energyband_low.stdev": 0.06828843802213669, "lowlevel.spectral_energyband_middle_high.mean": 0.0016968377167358994, "lowlevel.spectral_energyband_middle_high.stdev": 0.002454265719279647, "lowlevel.spectral_energyband_middle_low.mean": 0.011251895688474178, "lowlevel.spectral_energyband_middle_low.stdev": 0.019399043172597885, "lowlevel.spectral_entropy.mean": 7.527373790740967, "lowlevel.spectral_entropy.stdev": 0.4846658408641815, "lowlevel.spectral_flux.mean": 0.10545741021633148, "lowlevel.spectral_flux.stdev": 0.09573621302843094, "lowlevel.spectral_kurtosis.mean": 2.969064474105835, "lowlevel.spectral_kurtosis.stdev": 2.0847907066345215, "lowlevel.spectral_rms.mean": 0.00703840795904398, "lowlevel.spectral_rms.stdev": 0.00377794005908072, "lowlevel.spectral_rolloff.mean": 1678.08544921875, "lowlevel.spectral_rolloff.stdev": 3352.107421875, "lowlevel.spectral_skewness.mean": 1.508811116218567, "lowlevel.spectral_skewness.stdev": 0.4175269305706024, "lowlevel.spectral_spread.mean": 8432215.0, "lowlevel.spectral_spread.stdev": 2748734.25, "lowlevel.spectral_strongpeak.mean": 0.5911214351654053, "lowlevel.spectral_strongpeak.stdev": 0.43223652243614197, "lowlevel.zerocrossingrate.mean": 0.07357416301965714, "lowlevel.zerocrossingrate.stdev": 0.07030028849840164, "metadata.audio_properties.analysis.equal_loudness": 0.0, "metadata.audio_properties.analysis.length": 24.554649353027344, "metadata.audio_properties.analysis.sample_rate": 44100.0, "metadata.audio_properties.analysis.start_time": 0.0, "metadata.audio_properties.bit_rate": 121943.0, "metadata.audio_properties.length": 24.55466651916504, "metadata.audio_properties.lossless": 0.0, "metadata.audio_properties.number_channels": 1.0, "metadata.audio_properties.replay_gain": -6.526369094848633, "metadata.audio_properties.sample_rate": 48000.0, "rhythm.beats_count": 64.0, "rhythm.beats_loudness.mean": 0.10131355375051498, "rhythm.beats_loudness.stdev": 0.07050404697656631, "rhythm.bpm": 155.7990264892578, "rhythm.bpm_histogram_first_peak_bpm": 157.0, "rhythm.bpm_histogram_first_peak_weight": 0.4107142686843872, "rhythm.bpm_histogram_second_peak_bpm": 152.0, "rhythm.bpm_histogram_second_peak_spread": 0.0, "rhythm.bpm_histogram_second_peak_weight": 0.1111111119389534, "rhythm.danceability": 1.7212566137313843, "rhythm.onset_rate": 3.7449049949645996, "tonal.chords_changes_rate": 0.062264151871204376, "tonal.chords_number_rate": 0.011320754885673523, "tonal.chords_strength.mean": 0.5423486828804016, "tonal.chords_strength.stdev": 0.12212905287742615, "tonal.hpcp_crest.mean": 13.28378963470459, "tonal.hpcp_crest.stdev": 5.2834649085998535, "tonal.hpcp_entropy.mean": 1.9379702806472778, "tonal.hpcp_entropy.stdev": 0.6434169411659241, "tonal.key_edma.strength": 0.7868127226829529, "tonal.key_krumhansl.strength": 0.7871668338775635, "tonal.key_temperley.strength": 0.7815043330192566, "tonal.tuning_diatonic_strength": 0.6814387440681458, "tonal.tuning_equal_tempered_deviation": 0.3499448001384735, "tonal.tuning_frequency": 434.193115234375, "tonal.tuning_nontempered_energy_ratio": 0.9618080258369446, "lowlevel.barkbands.mean": [0.0017028995789587498, 0.04335008189082146, 0.0059160045348107815, 0.004471969325095415, 0.004578241612762213, 0.0007272447692230344, 0.0005583706079050899, 0.0003169575647916645, 0.0005339012714102864, 0.00030466774478554726, 0.0003003132587764412, 9.243191743735224e-05, 0.00010190443572355434, 0.0001822137419367209, 0.00010184667917201295, 8.786986290942878e-05, 0.00011042741243727505, 0.0001328329526586458, 0.00022991195146460086, 0.00019291433272883296, 0.0001275238610105589, 0.00010724146704887971, 0.00015154690481722355, 0.0001466773683205247, 0.00030363205587491393, 0.0005580420838668942, 1.9654202333185822e-05], "lowlevel.barkbands.stdev": [0.0025546511169523, 0.061463482677936554, 0.012827814556658268, 0.010654598474502563, 0.010171949863433838, 0.0012734468327835202, 0.0011306247906759381, 0.0009725840645842254, 0.0011641269084066153, 0.0008178691496141255, 0.0008254714775830507, 0.00022760973661206663, 0.00023622198204975575, 0.0007659552502445877, 0.00028137696790508926, 0.00021691857546102256, 0.0003682585956994444, 0.00036524140159599483, 0.0004595600184984505, 0.0004012657154817134, 0.00039941215072758496, 0.0003283334372099489, 0.00031795084942132235, 0.00027517531998455524, 0.0004888356779702008, 0.000931699585635215, 5.443075860966928e-05], "lowlevel.erbbands.mean": [1.4529776573181152, 8.745966911315918, 8.81061840057373, 11.663515090942383, 16.317045211791992, 15.035089492797852, 7.490123271942139, 6.3331217765808105, 6.708014011383057, 9.072526931762695, 6.8712568283081055, 12.655694961547852, 9.31424331665039, 11.360097885131836, 11.280261039733887, 3.9084672927856445, 5.209435939788818, 5.587273120880127, 9.800692558288574, 4.928090572357178, 4.7578535079956055, 6.037569046020508, 6.641966342926025, 10.56552505493164, 10.429420471191406, 9.246899604797363, 6.49813175201416, 4.39032506942749, 3.877068042755127, 4.525238990783691, 3.925179958343506, 2.70289945602417, 2.7791635990142822, 2.411386489868164, 2.6887292861938477, 2.138747215270996, 1.0411736965179443, 0.1860916018486023, 0.0035667584743350744, 0.0001836922747315839], "lowlevel.erbbands.stdev": [2.1946074962615967, 13.051309585571289, 17.59885597229004, 22.441287994384766, 43.83168411254883, 29.812665939331055, 12.445371627807617, 11.783306121826172, 14.529932022094727, 19.95646095275879, 19.322301864624023, 29.723237991333008, 25.236549377441406, 27.63779640197754, 30.340999603271484, 7.719771862030029, 12.091408729553223, 15.822739601135254, 35.75804901123047, 12.134283065795898, 11.22184944152832, 19.121999740600586, 18.023508071899414, 20.788841247558594, 19.959409713745117, 19.54331398010254, 17.84402847290039, 14.07168960571289, 12.755508422851562, 11.991883277893066, 7.85879373550415, 4.88522481918335, 5.407519817352295, 4.484950542449951, 4.15474271774292, 3.4187660217285156, 1.7488445043563843, 0.36709868907928467, 0.007004386745393276, 0.00022542427177540958], "lowlevel.gfcc.mean": [-5.9336419105529785, 51.704742431640625, -41.663814544677734, 37.14112854003906, -48.4123649597168, 16.45945930480957, -31.48164176940918, 21.785226821899414, -37.38642120361328, 10.476784706115723, -21.703462600708008, 4.033177375793457, -16.650196075439453], "lowlevel.melbands.mean": [0.012625976465642452, 0.006880095228552818, 0.0021543961483985186, 0.0011540851555764675, 0.00033796855132095516, 0.0001362766051897779, 0.00010658799146767706, 9.469306678511202e-05, 5.938438334851526e-05, 7.770828960929066e-05, 4.4309530494501814e-05, 4.4744730985257775e-05, 4.483295197132975e-05, 1.1577745681279339e-05, 1.0749507055152208e-05, 9.820860213949345e-06, 1.0784159712784458e-05, 1.825350227591116e-05, 7.0610417424177285e-06, 6.006744570186129e-06, 5.60981379749137e-06, 5.396373580879299e-06, 7.711696525802836e-06, 5.92610831517959e-06, 8.93684227776248e-06, 8.526687452103943e-06, 6.836610737082083e-06, 6.001595920679392e-06, 4.487020760279847e-06, 2.8638014555326663e-06, 2.4711462174309418e-06, 2.2726949282514397e-06, 1.899783342196315e-06, 2.8646545615629293e-06, 2.3447253170161275e-06, 1.851328079283121e-06, 1.588683289810433e-06, 1.91675940186542e-06, 2.011285005210084e-06, 2.0016607322759228e-06], "lowlevel.melbands.stdev": [0.01807200349867344, 0.01071052998304367, 0.004447351209819317, 0.002635112265124917, 0.0005525429733097553, 0.000251796911470592, 0.00022816764249000698, 0.00021542920148931444, 0.00015679281204938889, 0.00017595791723579168, 0.00012963908375240862, 0.00011814168829005212, 0.00012764340499415994, 2.746522477536928e-05, 2.1703996026189998e-05, 2.3389316993416287e-05, 3.4611020964803174e-05, 7.757332059554756e-05, 1.941054142662324e-05, 1.7530484910821542e-05, 1.4860956980555784e-05, 1.653172876103781e-05, 2.962750477308873e-05, 1.5359872122644447e-05, 1.820782017603051e-05, 1.7207481505465694e-05, 1.3710025086766109e-05, 1.3643283637065906e-05, 1.2472574780986179e-05, 8.603918104199693e-06, 8.755489034228958e-06, 7.756809282000177e-06, 5.5832956604717765e-06, 7.534053565905197e-06, 4.9431414481659885e-06, 3.396830379642779e-06, 3.0011588023626246e-06, 3.835808456642553e-06, 4.210638962831581e-06, 3.7553295442194212e-06], "lowlevel.melbands128.mean": [0.0016296094981953502, 0.01123399380594492, 0.018572205677628517, 0.013116694986820221, 0.0055723548866808414, 0.002726056147366762, 0.002350585302338004, 0.0021788303274661303, 0.0015883356099948287, 0.0012378599494695663, 0.0007936425390653312, 0.00045689110993407667, 0.00019681545381899923, 0.00020202284213155508, 0.0001740354491630569, 7.602053665323183e-05, 6.915554695297033e-05, 0.00013797689462080598, 0.00011257865116931498, 0.00011443463154137135, 7.573444599984214e-05, 5.9455851442180574e-05, 4.010703196399845e-05, 7.315443508559838e-05, 0.0001193485950352624, 4.467422695597634e-05, 7.168290903791785e-05, 3.270661545684561e-05, 3.806616223300807e-05, 5.042034536018036e-05, 4.554945553536527e-05, 3.436066253925674e-05, 7.345908670686185e-05, 2.187047357438132e-05, 1.364941090287175e-05, 9.026510269904975e-06, 7.5903526521869935e-06, 1.023701588565018e-05, 1.2546063771878835e-05, 1.473304564569844e-05, 6.230090093595209e-06, 7.85872180131264e-06, 9.678609785623848e-06, 6.170373126224149e-06, 3.1277155358111486e-05, 1.5669891581637785e-05, 1.2935150152770802e-05, 6.30969134363113e-06, 4.319402250985149e-06, 8.109818736556917e-06, 6.227030098671094e-06, 3.89186106986017e-06, 5.825570497108856e-06, 6.602391749765957e-06, 4.785943929164205e-06, 3.8107291402411647e-06, 6.730140285071684e-06, 1.0983974789269269e-05, 7.237325007736217e-06, 2.834826545949909e-06, 5.653554126183735e-06, 9.203732588503044e-06, 5.313774181558983e-06, 8.811752195470035e-06, 1.5112056644284166e-05, 6.610138370888308e-06, 5.859255907125771e-06, 9.114364729612134e-06, 5.456724920804845e-06, 6.675529220956378e-06, 6.440439847210655e-06, 5.369074642658234e-06, 5.403618160926271e-06, 4.589110631059157e-06, 3.1420545383298304e-06, 2.9846773941244464e-06, 2.8305782961979276e-06, 2.022277840296738e-06, 2.762938265732373e-06, 2.334034888917813e-06, 2.5080566956603434e-06, 2.287602001160849e-06, 1.6947261656241608e-06, 1.7389319282301585e-06, 2.0843506263190648e-06, 2.675029691090458e-06, 3.2881971492315643e-06, 3.0203646019799635e-06, 2.0201846382406075e-06, 2.1570417629845906e-06, 2.117325266226544e-06, 1.7551453765918268e-06, 1.386446342621639e-06, 1.549991225147096e-06, 1.6444446373498067e-06, 2.0240001958882203e-06, 1.8939682604468544e-06, 1.852021114245872e-06, 2.1976018160785316e-06, 2.1580553948297165e-06, 1.4802820942350081e-06, 2.2067026748118224e-06, 1.9673188944580033e-06, 3.369792239027447e-06, 2.7313715236232383e-06, 3.4420261272316566e-06, 3.5077287066087592e-06, 3.1693944038124755e-06, 4.129783519601915e-06, 4.029957835882669e-06, 3.498005980873131e-06, 3.854198439512402e-06, 3.1421288895217003e-06, 3.147146799165057e-06, 3.1990323350328254e-06, 2.5394128897460178e-06, 8.636383199700504e-07, 3.071643561725068e-08, 4.508673434600041e-10, 8.980179100337438e-11, 5.5477834132178216e-11, 1.5300436265186512e-11, 1.054765649821654e-11, 1.0315014467576766e-11, 1.0042339355920138e-11, 9.705838563411895e-12, 9.510607579255037e-12, 9.43640044576144e-12], "lowlevel.melbands128.stdev": [0.0024753271136432886, 0.018223607912659645, 0.0282534621655941, 0.02096048928797245, 0.01190716028213501, 0.005416280589997768, 0.004583572503179312, 0.005957029294222593, 0.004880005493760109, 0.003040952840819955, 0.0016023851931095123, 0.0009078467846848071, 0.00044394945143722, 0.0004086689732503146, 0.00038597590173594654, 0.0002194917615270242, 0.0001989039737964049, 0.00036031045601703227, 0.0002563440066296607, 0.0003459748695604503, 0.00026669405633583665, 0.000281394284684211, 0.00020296897855587304, 0.00020107239834032953, 0.0003625336103141308, 0.00011457748041721061, 0.0003063837648369372, 0.00011999117123195902, 0.0001927798002725467, 0.00016390848031733185, 0.00017240292800124735, 0.00011077625094912946, 0.0002533054503146559, 7.048885890981182e-05, 4.5453853090293705e-05, 2.5591676603653468e-05, 2.548964403104037e-05, 2.898330239986535e-05, 3.194082455593161e-05, 5.0531260058050975e-05, 2.123865306202788e-05, 2.8720740374410525e-05, 4.1595187212806195e-05, 2.57427691394696e-05, 0.00018532213289290667, 7.641382399015129e-05, 5.09990168211516e-05, 2.5933619326679036e-05, 1.615095061424654e-05, 3.0489980417769402e-05, 2.952441900561098e-05, 1.2382301065372303e-05, 2.2763175365980715e-05, 2.1784442651551217e-05, 1.67358411999885e-05, 1.297768631047802e-05, 4.1277442505816e-05, 5.4753963922848925e-05, 3.3029504265869036e-05, 9.082774340640754e-06, 1.7945012587006204e-05, 2.773459709715098e-05, 1.20286949822912e-05, 2.773666346911341e-05, 4.2253810534020886e-05, 1.500172493251739e-05, 1.4599390851799399e-05, 2.290130578330718e-05, 1.3058132026344538e-05, 1.8056169210467488e-05, 1.5940076991682872e-05, 1.6071782738436013e-05, 1.384006827720441e-05, 1.604936915100552e-05, 1.0258445399813354e-05, 9.899954420689028e-06, 8.84998280525906e-06, 6.31602688372368e-06, 1.2333376616879832e-05, 8.24591097625671e-06, 9.129862519330345e-06, 8.94936420081649e-06, 6.787380698369816e-06, 4.755588179250481e-06, 6.391620445356239e-06, 8.063288078119513e-06, 8.965304914454464e-06, 7.237774298118893e-06, 4.917922069580527e-06, 4.31720172855421e-06, 4.204155175102642e-06, 3.5039815884374548e-06, 2.6344932848587632e-06, 3.5077309803455137e-06, 3.362492861924693e-06, 4.04847696700017e-06, 4.439289114088751e-06, 4.049850758747198e-06, 5.019207037548767e-06, 5.080208666186081e-06, 3.5740072235057596e-06, 4.151484063186217e-06, 4.206369794701459e-06, 5.726762537960894e-06, 4.67615154775558e-06, 5.961957413092023e-06, 6.1966020439285785e-06, 5.6295089052582625e-06, 6.861026122351177e-06, 7.142463800846599e-06, 7.289166660484625e-06, 6.411902631953126e-06, 5.659046109940391e-06, 5.692165814252803e-06, 6.369763468683232e-06, 5.6392382248304784e-06, 2.2358585738402326e-06, 1.495670005624561e-07, 7.379566291376705e-09, 2.513925512204196e-09, 1.4330143738305878e-09, 1.4316930974089814e-10, 1.8613140542744766e-11, 1.8273675975177817e-11, 1.7994449680314162e-11, 1.7771078011930008e-11, 1.7610872829476598e-11, 1.7512314515188976e-11], "lowlevel.mfcc.mean": [-681.133544921875, 101.43711853027344, 52.918697357177734, 36.20853805541992, 12.306300163269043, 4.307218074798584, 17.5385799407959, 5.944865703582764, -0.12697602808475494, 8.90834903717041, -1.768521785736084, -3.9470088481903076, 0.5154803395271301], "lowlevel.spectral_contrast_coeffs.mean": [-0.6729758381843567, -0.7426285743713379, -0.773559033870697, -0.8025084137916565, -0.7847190499305725, -0.7792439460754395], "lowlevel.spectral_contrast_coeffs.stdev": [0.08891469240188599, 0.0761822983622551, 0.07858174294233322, 0.061948396265506744, 0.057489022612571716, 0.03728208690881729], "lowlevel.spectral_contrast_valleys.mean": [-6.593961715698242, -7.43631649017334, -8.313076972961426, -8.68485164642334, -8.097396850585938, -10.122925758361816], "lowlevel.spectral_contrast_valleys.stdev": [1.1748237609863281, 0.5721393823623657, 0.6914628744125366, 0.8674593567848206, 0.7660263180732727, 0.7999199032783508], "rhythm.beats_loudness_band_ratio.mean": [0.7756051421165466, 0.08947201073169708, 0.032123174518346786, 0.0170985646545887, 0.013935155235230923, 0.08663801103830338], "rhythm.beats_loudness_band_ratio.stdev": [0.23613519966602325, 0.11634250730276108, 0.05228721722960472, 0.030522488057613373, 0.0211213119328022, 0.10349436104297638], "tonal.hpcp.mean": [0.14810346066951752, 0.17202669382095337, 0.10744418203830719, 0.04920526593923569, 0.0217035710811615, 0.02325761877000332, 0.07454147189855576, 0.1746978908777237, 0.1448581963777542, 0.04857875034213066, 0.03192188963294029, 0.04820731654763222, 0.18040047585964203, 0.21949458122253418, 0.0994434729218483, 0.05713791027665138, 0.06639862060546875, 0.05013145133852959, 0.0289235170930624, 0.022290796041488647, 0.026881253346800804, 0.10332876443862915, 0.22125348448753357, 0.18220524489879608, 0.07646195590496063, 0.05343085154891014, 0.06966303288936615, 0.11034103482961655, 0.11944989114999771, 0.07593242824077606, 0.039967071264982224, 0.03461535647511482, 0.03694616258144379, 0.04881112650036812, 0.0628868043422699, 0.08355513215065002], "tonal.hpcp.stdev": [0.2936251759529114, 0.3210027515888214, 0.23932968080043793, 0.1676129549741745, 0.10723181068897247, 0.10990121960639954, 0.17154744267463684, 0.30346351861953735, 0.2740201950073242, 0.15029628574848175, 0.1346631646156311, 0.15064674615859985, 0.3329679071903229, 0.35689690709114075, 0.1953216791152954, 0.18648208677768707, 0.21617379784584045, 0.17031115293502808, 0.10570026189088821, 0.1059761494398117, 0.10581865906715393, 0.2091771960258484, 0.3495272099971771, 0.29277661442756653, 0.20007027685642242, 0.175333172082901, 0.19666153192520142, 0.2717602252960205, 0.2718881368637085, 0.1902529001235962, 0.13670749962329865, 0.13596630096435547, 0.1400989443063736, 0.14898084104061127, 0.16396702826023102, 0.1990741640329361], "rhythm.beats_position": [0.39473921060562134, 0.7894784212112427, 1.172607660293579, 1.5557368993759155, 1.9504761695861816, 2.3336052894592285, 2.7167346477508545, 3.088253974914551, 3.4713830947875977, 3.842902421951294, 4.22603178024292, 4.597550868988037, 4.980679988861084, 5.363809585571289, 5.735328674316406, 6.106847763061523, 6.501587390899658, 6.884716510772705, 7.267845630645752, 7.639364719390869, 8.034104347229004, 8.405623435974121, 8.777142524719238, 9.148661613464355, 9.543400764465332, 9.914920806884766, 10.309659957885742, 10.68117904663086, 11.052698135375977, 11.435827255249023, 11.81895637512207, 12.190476417541504, 12.57360553741455, 12.956734657287598, 13.328253746032715, 13.711382865905762, 14.094511985778809, 14.477641105651855, 14.860771179199219, 15.232290267944336, 15.615419387817383, 15.99854850769043, 16.370067596435547, 16.753196716308594, 17.13632583618164, 17.519454956054688, 17.902584075927734, 18.27410316467285, 18.6456241607666, 19.02875328063965, 19.411882400512695, 19.783401489257812, 20.17814064025879, 20.549659729003906, 20.932788848876953, 21.31591796875, 21.687437057495117, 22.070566177368164, 22.45369529724121, 22.825214385986328, 23.208343505859375, 23.591472625732422, 23.962993621826172, 24.34612274169922], "rhythm.bpm_histogram": [0.0, 0.0, 0.0, 0.0, 0.0, 0.0, 0.0, 0.0, 0.0, 0.0, 0.0, 0.0, 0.0, 0.0, 0.0, 0.0, 0.0, 0.0, 0.0, 0.0, 0.0, 0.0, 0.0, 0.0, 0.0, 0.0, 0.0, 0.0, 0.0, 0.0, 0.0, 0.0, 0.0, 0.0, 0.0, 0.0, 0.0, 0.0, 0.0, 0.0, 0.0, 0.0, 0.0, 0.0, 0.0, 0.0, 0.0, 0.0, 0.0, 0.0, 0.0, 0.0, 0.0, 0.0, 0.0, 0.0, 0.0, 0.0, 0.0, 0.0, 0.0, 0.0, 0.0, 0.0, 0.0, 0.0, 0.0, 0.0, 0.0, 0.0, 0.0, 0.0, 0.0, 0.0, 0.0, 0.0, 0.0, 0.0, 0.0, 0.0, 0.0, 0.0, 0.0, 0.0, 0.0, 0.0, 0.0, 0.0, 0.0, 0.0, 0.0, 0.0, 0.0, 0.0, 0.0, 0.0, 0.0, 0.0, 0.0, 0.0, 0.0, 0.0, 0.0, 0.0, 0.0, 0.0, 0.0, 0.0, 0.0, 0.0, 0.0, 0.0, 0.0, 0.0, 0.0, 0.0, 0.0, 0.0, 0.0, 0.0, 0.0, 0.0, 0.0, 0.0, 0.0, 0.0, 0.0, 0.0, 0.0, 0.0, 0.0, 0.0, 0.0, 0.0, 0.0, 0.0, 0.0, 0.0, 0.0, 0.0, 0.0, 0.0, 0.0, 0.0, 0.0, 0.0, 0.0, 0.0, 0.0, 0.0, 0.0, 0.0, 0.1111111119389534, 0.0, 0.0, 0.0, 0.0, 0.523809552192688, 0.0, 0.0, 0.0, 0.3650793731212616, 0.0, 0.0, 0.0, 0.0, 0.0, 0.0, 0.0, 0.0, 0.0, 0.0, 0.0, 0.0, 0.0, 0.0, 0.0, 0.0, 0.0, 0.0, 0.0, 0.0, 0.0, 0.0, 0.0, 0.0, 0.0, 0.0, 0.0, 0.0, 0.0, 0.0, 0.0, 0.0, 0.0, 0.0, 0.0, 0.0, 0.0, 0.0, 0.0, 0.0, 0.0, 0.0, 0.0, 0.0, 0.0, 0.0, 0.0, 0.0, 0.0, 0.0, 0.0, 0.0, 0.0, 0.0, 0.0, 0.0, 0.0, 0.0, 0.0, 0.0, 0.0, 0.0, 0.0, 0.0, 0.0, 0.0, 0.0, 0.0, 0.0, 0.0, 0.0, 0.0, 0.0, 0.0, 0.0, 0.0, 0.0, 0.0, 0.0, 0.0, 0.0, 0.0, 0.0, 0.0, 0.0, 0.0, 0.0, 0.0], "tonal.chords_histogram": [55.09434127807617, 3.0188679695129395, 22.830188751220703, 0.0, 0.0, 0.0, 4.905660152435303, 0.0, 0.0, 0.0, 0.0, 0.0, 0.0, 0.0, 0.0, 0.0, 0.0, 0.0, 0.0, 1.8867924213409424, 0.0, 0.5660377144813538, 0.0, 11.698113441467285], "tonal.thpcp": [1.0, 0.8235135674476624, 0.34558531641960144, 0.24149157106876373, 0.3148562014102936, 0.49870869517326355, 0.5398780107498169, 0.3431920111179352, 0.18063928186893463, 0.15645112097263336, 0.1669856756925583, 0.2206117808818817, 0.28422966599464417, 0.3776443600654602, 0.6693836450576782, 0.7775095105171204, 0.4856157600879669, 0.2223931849002838, 0.09809368848800659, 0.10511752218008041, 0.336905300617218, 0.7895825505256653, 0.6547160148620605, 0.21956151723861694, 0.1442774534225464, 0.21788275241851807, 0.8153565526008606, 0.992050290107727, 0.4494549334049225, 0.25824636220932007, 0.30010202527046204, 0.22657926380634308, 0.13072569668293, 0.10074777156114578, 0.12149527668952942, 0.4670152962207794], "lowlevel.gfcc.cov": [[2982.1611328125, -140.0264434814453, -42.29877853393555, 103.92628479003906, 356.75390625, 190.7598419189453, 214.04074096679688, 53.37427520751953, -26.754873275756836, 103.6500244140625, -29.59438133239746, 4.319166660308838, 16.30118751525879], [-140.0264434814453, 1442.7998046875, 222.84950256347656, 259.28955078125, 442.02435302734375, 346.5898132324219, 456.5680847167969, 371.38763427734375, 57.770721435546875, -24.134235382080078, 236.03334045410156, -168.98660278320312, 60.0516471862793], [-42.29877853393555, 222.84950256347656, 1586.7266845703125, 630.8858032226562, 137.48072814941406, 484.4720458984375, 346.3605651855469, 191.6465606689453, 264.2918701171875, 76.63014221191406, 37.79707717895508, 136.49961853027344, -95.73202514648438], [103.92628479003906, 259.28955078125, 630.8858032226562, 707.2323608398438, 389.9044189453125, 177.87408447265625, 134.08026123046875, 262.1033935546875, 217.8423614501953, -4.764325141906738, 72.43360137939453, 52.871131896972656, 26.408203125], [356.75390625, 442.02435302734375, 137.48072814941406, 389.9044189453125, 594.2786254882812, 232.14735412597656, 228.1125946044922, 275.3965148925781, 105.14138793945312, 28.868080139160156, 104.92198944091797, -23.78898048400879, 77.29212188720703], [190.7598419189453, 346.5898132324219, 484.4720458984375, 177.87408447265625, 232.14735412597656, 567.1227416992188, 395.7945861816406, 152.52503967285156, 63.187381744384766, 73.60791015625, 94.57966613769531, -65.49873352050781, -1.7969127893447876], [214.04074096679688, 456.5680847167969, 346.3605651855469, 134.08026123046875, 228.1125946044922, 395.7945861816406, 449.66412353515625, 218.88941955566406, 49.2704963684082, 65.30709075927734, 107.84190368652344, -51.49821090698242, -8.461822509765625], [53.37427520751953, 371.38763427734375, 191.6465606689453, 262.1033935546875, 275.3965148925781, 152.52503967285156, 218.88941955566406, 323.2793273925781, 136.19789123535156, 3.68139386177063, 93.79854583740234, -15.950167655944824, 34.346832275390625], [-26.754873275756836, 57.770721435546875, 264.2918701171875, 217.8423614501953, 105.14138793945312, 63.187381744384766, 49.2704963684082, 136.19789123535156, 204.80422973632812, 52.34383010864258, 18.082576751708984, 37.406978607177734, 4.674596309661865], [103.6500244140625, -24.134235382080078, 76.63014221191406, -4.764325141906738, 28.868080139160156, 73.60791015625, 65.30709075927734, 3.68139386177063, 52.34383010864258, 113.93697357177734, 35.131954193115234, 8.642938613891602, -3.4311132431030273], [-29.59438133239746, 236.03334045410156, 37.79707717895508, 72.43360137939453, 104.92198944091797, 94.57966613769531, 107.84190368652344, 93.79854583740234, 18.082576751708984, 35.131954193115234, 134.722900390625, 5.321480751037598, 9.270906448364258], [4.319166660308838, -168.98660278320312, 136.49961853027344, 52.871131896972656, -23.78898048400879, -65.49873352050781, -51.49821090698242, -15.950167655944824, 37.406978607177734, 8.642938613891602, 5.321480751037598, 137.7362518310547, -1.9474540948867798], [16.30118751525879, 60.0516471862793, -95.73202514648438, 26.408203125, 77.29212188720703, -1.7969127893447876, -8.461822509765625, 34.346832275390625, 4.674596309661865, -3.4311132431030273, 9.270906448364258, -1.9474540948867798, 79.80751037597656]], "lowlevel.gfcc.icov": [[0.0004362124891486019, 7.686465687584132e-05, 0.0001722794258967042, -0.0001854559377534315, -0.0002859285450540483, -7.02212200849317e-05, -0.0002805553376674652, -3.504441338009201e-05, 0.0004116583149880171, -0.000574673293158412, 0.0006227961857803166, -0.00030687288381159306, 0.00025310239288955927], [7.686465687584132e-05, 0.002693472197279334, -0.0013498712796717882, 0.001463620108552277, -0.0016620451351627707, 0.0022506832610815763, -0.0026909643784165382, 0.0014450420858338475, -0.002068381756544113, 0.00402076356112957, -0.005030795931816101, 0.004492342937737703, -0.0024047924671322107], [0.0001722794258967042, -0.0013498712796717882, 0.0035489872097969055, -0.0035234654787927866, 0.0023935541976243258, -0.0032290895469486713, 0.0003626596590038389, -0.0008961097919382155, 0.0010908733820542693, -0.0031167836859822273, 0.004661789629608393, -0.005146775860339403, 0.0035718472208827734], [-0.0001854559377534315, 0.001463620108552277, -0.0035234654787927866, 0.0072539811953902245, -0.00441111670807004, 0.0024985577911138535, 9.228810085915029e-05, 0.0009847675682976842, -0.004519737791270018, 0.005965413060039282, -0.005533439107239246, 0.004115118179470301, -0.0025115585885941982], [-0.0002859285450540483, -0.0016620451351627707, 0.0023935541976243258, -0.00441111670807004, 0.0065948874689638615, -0.0030300281941890717, 0.0012971529504284263, -0.0034874717239290476, 0.0030818034429103136, -0.004562492948025465, 0.003855775808915496, -0.0036306388210505247, -9.017092088470235e-05], [-7.02212200849317e-05, 0.0022506832610815763, -0.0032290895469486713, 0.0024985577911138535, -0.0030300281941890717, 0.009271085262298584, -0.007424468640238047, 0.004988794680684805, -0.003898352850228548, 0.004851639736443758, -0.006791440770030022, 0.007641144096851349, -0.004758024588227272], [-0.0002805553376674652, -0.0026909643784165382, 0.0003626596590038389, 9.228810085915029e-05, 0.0012971529504284263, -0.007424468640238047, 0.013933626003563404, -0.009091428481042385, 0.006730710156261921, -0.007892083376646042, 0.0048561724834144115, -0.00428620632737875, 0.005050974898040295], [-3.504441338009201e-05, 0.0014450420858338475, -0.0008961097919382155, 0.0009847675682976842, -0.0034874717239290476, 0.004988794680684805, -0.009091428481042385, 0.01559939980506897, -0.010994265787303448, 0.010450012050569057, -0.008327350951731205, 0.005049778614193201, -0.004484722390770912], [0.0004116583149880171, -0.002068381756544113, 0.0010908733820542693, -0.004519737791270018, 0.0030818034429103136, -0.003898352850228548, 0.006730710156261921, -0.010994265787303448, 0.018075430765748024, -0.014209955930709839, 0.009716210886836052, -0.006315323058515787, 0.0036967552732676268], [-0.000574673293158412, 0.00402076356112957, -0.0031167836859822273, 0.005965413060039282, -0.004562492948025465, 0.004851639736443758, -0.007892083376646042, 0.010450012050569057, -0.014209955930709839, 0.025020720437169075, -0.014875712804496288, 0.008313329890370369, -0.005588008556514978], [0.0006227961857803166, -0.005030795931816101, 0.004661789629608393, -0.005533439107239246, 0.003855775808915496, -0.006791440770030022, 0.0048561724834144115, -0.008327350951731205, 0.009716210886836052, -0.014875712804496288, 0.024324702098965645, -0.012946859933435917, 0.0069425348192453384], [-0.00030687288381159306, 0.004492342937737703, -0.005146775860339403, 0.004115118179470301, -0.0036306388210505247, 0.007641144096851349, -0.00428620632737875, 0.005049778614193201, -0.006315323058515787, 0.008313329890370369, -0.012946859933435917, 0.01988484524190426, -0.00707599613815546], [0.00025310239288955927, -0.0024047924671322107, 0.0035718472208827734, -0.0025115585885941982, -9.017092088470235e-05, -0.004758024588227272, 0.005050974898040295, -0.004484722390770912, 0.0036967552732676268, -0.005588008556514978, 0.0069425348192453384, -0.00707599613815546, 0.02041349560022354]], "lowlevel.mfcc.cov": [[3021.480712890625, -171.07919311523438, -554.4891357421875, 15.707972526550293, 88.94784545898438, 108.71949005126953, 148.3952178955078, -62.93745422363281, 56.97552490234375, 87.94024658203125, -25.599916458129883, -106.52224731445312, 25.10847282409668], [-171.07919311523438, 1068.804931640625, 14.526132583618164, 61.0966682434082, 112.50035858154297, 76.65298461914062, 478.1236267089844, 212.52645874023438, 96.87593078613281, 258.55767822265625, 108.65096282958984, 38.58910369873047, 82.7611312866211], [-554.4891357421875, 14.526132583618164, 1464.9671630859375, 229.41632080078125, 82.6422119140625, 370.0955505371094, 127.87755584716797, 321.1517639160156, 193.90606689453125, 38.232120513916016, 232.95455932617188, 201.8881378173828, 111.45014953613281], [15.707972526550293, 61.0966682434082, 229.41632080078125, 589.8645629882812, 385.7377624511719, -19.126811981201172, 32.08237838745117, 214.15757751464844, 146.6252899169922, 29.546920776367188, 65.40653991699219, 154.4056854248047, 91.8415298461914], [88.94784545898438, 112.50035858154297, 82.6422119140625, 385.7377624511719, 496.6879577636719, 63.242164611816406, 131.93527221679688, 188.2451629638672, 157.9085693359375, 109.45716857910156, 59.29986572265625, 96.75501251220703, 68.34900665283203], [108.71949005126953, 76.65298461914062, 370.0955505371094, -19.126811981201172, 63.242164611816406, 368.56982421875, 217.44761657714844, 103.10011291503906, 92.04243469238281, 126.70804595947266, 100.26506042480469, 19.00008773803711, 41.25738525390625], [148.3952178955078, 478.1236267089844, 127.87755584716797, 32.08237838745117, 131.93527221679688, 217.44761657714844, 551.9971923828125, 225.30792236328125, 107.8128433227539, 249.0471954345703, 114.01980590820312, 19.68977928161621, 78.86188507080078], [-62.93745422363281, 212.52645874023438, 321.1517639160156, 214.15757751464844, 188.2451629638672, 103.10011291503906, 225.30792236328125, 312.5462646484375, 149.65174865722656, 110.3365249633789, 114.46865844726562, 113.03429412841797, 83.82022857666016], [56.97552490234375, 96.87593078613281, 193.90606689453125, 146.6252899169922, 157.9085693359375, 92.04243469238281, 107.8128433227539, 149.65174865722656, 203.9049530029297, 120.90745544433594, 67.79139709472656, 49.536922454833984, 62.94222640991211], [87.94024658203125, 258.55767822265625, 38.232120513916016, 29.546920776367188, 109.45716857910156, 126.70804595947266, 249.0471954345703, 110.3365249633789, 120.90745544433594, 282.4671325683594, 83.40782165527344, 4.491143703460693, 57.865020751953125], [-25.599916458129883, 108.65096282958984, 232.95455932617188, 65.40653991699219, 59.29986572265625, 100.26506042480469, 114.01980590820312, 114.46865844726562, 67.79139709472656, 83.40782165527344, 150.1591339111328, 87.77690887451172, 48.99008560180664], [-106.52224731445312, 38.58910369873047, 201.8881378173828, 154.4056854248047, 96.75501251220703, 19.00008773803711, 19.68977928161621, 113.03429412841797, 49.536922454833984, 4.491143703460693, 87.77690887451172, 168.50279235839844, 61.27617645263672], [25.10847282409668, 82.7611312866211, 111.45014953613281, 91.8415298461914, 68.34900665283203, 41.25738525390625, 78.86188507080078, 83.82022857666016, 62.94222640991211, 57.865020751953125, 48.99008560180664, 61.27617645263672, 105.95990753173828]], "lowlevel.mfcc.icov": [[0.0004322013119235635, 0.00018921226728707552, 0.0003170511336065829, -0.00021200923947617412, 0.00011205219925614074, -0.0003174858575221151, -0.0002397142961854115, 0.00011996934335911646, -0.0002724966616369784, 0.0001661877176957205, -0.00024593150010332465, 0.00024852939532138407, -0.00022397784050554037], [0.00018921226728707552, 0.0017931266920641065, 0.0001429950207239017, -0.00015058382996357977, 0.00020426957053132355, 0.0006130806868895888, -0.0015769096789881587, -4.2211104300804436e-05, -3.597613249439746e-05, -0.0005187008646316826, -0.00028802448650822043, -6.882400339236483e-05, -0.00015111223910935223], [0.0003170511336065829, 0.0001429950207239017, 0.0018129394156858325, -0.0006771370535716414, 0.0009074291447177529, -0.00182751240208745, 0.0003978900203946978, -0.0010846405057236552, -0.0006751110195182264, 0.0008233881671912968, -0.0011696598958224058, -0.00014345909585244954, -0.00024353757908102125], [-0.00021200923947617412, -0.00015058382996357977, -0.0006771370535716414, 0.0051560974679887295, -0.0034154970198869705, 0.0014842344680801034, 0.0006827219040133059, -0.0011747026583179832, -0.00024854580988176167, 0.0004386969085317105, 0.0006585794035345316, -0.0013770541409030557, -0.0011427176650613546], [0.00011205219925614074, 0.00020426957053132355, 0.0009074291447177529, -0.0034154970198869705, 0.005486058071255684, -0.001321366406045854, -0.0004437404277268797, -0.0005045635625720024, -0.0015026602195575833, -0.0006163741345517337, 0.0005116065149195492, -0.0006847951444797218, 0.0009136844892054796], [-0.0003174858575221151, 0.0006130806868895888, -0.00182751240208745, 0.0014842344680801034, -0.001321366406045854, 0.006423380225896835, -0.0022382568567991257, 0.001397080603055656, -0.0006038632127456367, -0.0007443936774507165, -0.0011377924820408225, 0.0006065372726880014, 8.45921749714762e-05], [-0.0002397142961854115, -0.0015769096789881587, 0.0003978900203946978, 0.0006827219040133059, -0.0004437404277268797, -0.0022382568567991257, 0.0063907369039952755, -0.003794706892222166, 0.0020917311776429415, -0.0022027234081178904, -0.0003026931663043797, 0.001385404379107058, -0.001019450486637652], [0.00011996934335911646, -4.2211104300804436e-05, -0.0010846405057236552, -0.0011747026583179832, -0.0005045635625720024, 0.001397080603055656, -0.003794706892222166, 0.010372623801231384, -0.003702852176502347, 0.0010807886719703674, -0.0011086153099313378, -0.0022867959924042225, 8.331117896887008e-06], [-0.0002724966616369784, -3.597613249439746e-05, -0.0006751110195182264, -0.00024854580988176167, -0.0015026602195575833, -0.0006038632127456367, 0.0020917311776429415, -0.003702852176502347, 0.011338070966303349, -0.003839341225102544, 0.00018324810662306845, 0.0014270500978454947, -0.001953368540853262], [0.0001661877176957205, -0.0005187008646316826, 0.0008233881671912968, 0.0004386969085317105, -0.0006163741345517337, -0.0007443936774507165, -0.0022027234081178904, 0.0010807886719703674, -0.003839341225102544, 0.008796199224889278, -0.0032720111776143312, 0.001971128163859248, -0.0015587515663355589], [-0.00024593150010332465, -0.00028802448650822043, -0.0011696598958224058, 0.0006585794035345316, 0.0005116065149195492, -0.0011377924820408225, -0.0003026931663043797, -0.0011086153099313378, 0.00018324810662306845, -0.0032720111776143312, 0.015602532774209976, -0.007020420394837856, 0.0006820693961344659], [0.00024852939532138407, -6.882400339236483e-05, -0.00014345909585244954, -0.0013770541409030557, -0.0006847951444797218, 0.0006065372726880014, 0.001385404379107058, -0.0022867959924042225, 0.0014270500978454947, 0.001971128163859248, -0.007020420394837856, 0.014053252525627613, -0.004482445307075977], [-0.00022397784050554037, -0.00015111223910935223, -0.00024353757908102125, -0.0011427176650613546, 0.0009136844892054796, 8.45921749714762e-05, -0.001019450486637652, 8.331117896887008e-06, -0.001953368540853262, -0.0015587515663355589, 0.0006820693961344659, -0.004482445307075977, 0.015273496508598328]], "metadata.audio_properties.analysis.downmix": "mix", "metadata.audio_properties.codec": "mp3", "metadata.audio_properties.md5_encoded": "a137fde9621028e9ffd408f3dc252c5f", "metadata.tags.file_name": "1182279059623923753.mp3", "metadata.version.essentia": "2.1-beta6-dev", "metadata.version.essentia_git_sha": "v2.1_beta5-1110-g77a6a954", "metadata.version.extractor": "music 2.0", "tonal.chords_key": "A", "tonal.chords_scale": "major", "tonal.key_edma.key": "A", "tonal.key_edma.scale": "major", "tonal.key_krumhansl.key": "A", "tonal.key_krumhansl.scale": "major", "tonal.key_temperley.key": "A", "tonal.key_temperley.scale": "major", "metadata.tags.encoding": ["Lavf58.45.100"]}, "essentia_models": [{"model_name": "genre_dortmund", "activations": {"alternative": "0.0075826645", "blues": "0.0018459375", "electronic": "0.06787171", "folkcountry": "0.0056927246", "funksoulrnb": "0.040990427", "jazz": "0.010544299", "pop": "0.5063495", "raphiphop": "0.14956684", "rock": "0.01509911"}}, {"model_name": "genre_rosamerica", "activations": {"classic": "0.0004697504", "dance": "0.0030469836", "hip hop": "0.003429336", "jazz": "0.0012598427", "pop": "0.6338226", "rhythm and blues": "0.4806469", "rock": "0.001955984", "speech": "0.0009835021"}}, {"model_name": "genre_tzanetakis", "activations": {"blues": "0.0001831334", "classic": "0.00020146303", "country": "0.0036880893", "disco": "0.008660839", "hip hop": "0.0057447", "jazz": "0.00017215335", "metal": "0.0012405128", "pop": "0.92845416", "reggae": "0.04369385", "rock": "0.09589547"}}, {"model_name": "genre_electronic", "activations": {"ambient": "0.10571", "dnb": "0.10964962", "house": "0.3906202", "techno": "0.50598514", "trance": "0.009370533"}}, {"model_name": "mood_acoustic", "activations": {"acoustic": "0.004626669", "not acoustic": "0.926021"}}, {"model_name": "mood_electronic", "activations": {"electronic": "0.5725187", "not electronic": "0.42765504"}}, {"model_name": "mood_aggressive", "activations": {"aggressive": "0.16894178", "not aggressive": "0.9944456"}}, {"model_name": "mood_relaxed", "activations": {"not relaxed": "0.18135592", "relaxed": "0.6680975"}}, {"model_name": "mood_happy", "activations": {"happy": "0.3207644", "not happy": "0.57528025"}}, {"model_name": "mood_sad", "activations": {"not sad": "0.14443402", "sad": "0.93399197"}}, {"model_name": "mood_party", "activations": {"not party": "0.9164667", "party": "0.102137506"}}, {"model_name": "danceability", "activations": {"danceable": "0.9974072", "not danceable": "0.012122471"}}, {"model_name": "gender", "activations": {"female": "0.6620213", "male": "0.3270288"}}, {"model_name": "tonal_atonal", "activations": {"tonal": "0.9708455", "atonal": "0.073405854"}}, {"model_name": "voice_instrumental", "activations": {"instrumental": "0.09494735", "voice": "0.7350231"}}], "musicnn_penultimate": [[-0.14655190706253052, -0.12702879309654236, -0.2848263680934906, 0.24447843432426453, -0.35315048694610596, 0.339302659034729, -0.2574056386947632, 0.587856650352478, -0.07686340808868408, 0.8310258984565735, 0.12301859259605408, 0.45824724435806274, -0.11183390021324158, -0.18863335251808167, 0.22362574934959412, -0.8824635744094849, -0.2285488247871399, 0.25690045952796936, 1.1133325099945068, 0.6885517835617065, 1.2239924669265747, 0.2605336904525757, 1.0286924839019775, -0.5004634857177734, -0.4373127818107605, 0.5504778623580933, 0.5429327487945557, 1.1074309349060059, 0.29141852259635925, -0.17371639609336853, 0.04657697677612305, -0.24058040976524353, -0.6885523796081543, -0.1293015033006668, 0.26443085074424744, -0.10921159386634827, 0.21545898914337158, 1.7233703136444092, -0.3735160231590271, -0.18397580087184906, -0.13594649732112885, 0.413409948348999, -0.28197017312049866, -0.22951865196228027, -0.3001438081264496, -0.23910605907440186, 0.6208609342575073, 0.690345287322998, -0.25552937388420105, 0.5086168050765991, 0.993882417678833, -0.1851099133491516, 0.18729135394096375, -0.2301802635192871, -0.28901156783103943, 1.6469874382019043, -0.29257306456565857, 0.6764389872550964, -0.30312246084213257, -0.30667585134506226, -0.24988946318626404, -0.06140737235546112, -0.39138007164001465, -0.2741222679615021, -0.29662537574768066, 0.8833755850791931, 0.4485108554363251, 0.7409955859184265, 0.6135613322257996, -0.40455350279808044, 0.17236006259918213, -0.27082300186157227, -0.3255459666252136, 0.14588508009910583, -0.3767146170139313, -0.3091731369495392, -0.7182999849319458, 0.34830108284950256, -0.21875137090682983, 0.6556558012962341, -0.3005925416946411, -0.21734273433685303, 1.2743914127349854, -0.3638487756252289, 1.0220792293548584, -0.3128108084201813, -0.24609725177288055, -0.335518479347229, -0.33807578682899475, -0.18530058860778809, -0.3638553023338318, 0.02587553858757019, -0.14375922083854675, 0.5482443571090698, -0.4431609809398651, -0.3032689392566681, -0.7176907658576965, 0.48989614844322205, 0.25951629877090454, 0.7248169183731079, -0.35263898968696594, -0.11176306009292603, -0.1758536994457245, -0.30536577105522156, -0.06311528384685516, -0.23980242013931274, -0.15264460444450378, -0.19663754105567932, -0.2404516339302063, -0.22667694091796875, 2.2526473999023438, 0.2785699963569641, 0.3663039803504944, -0.2637975215911865, 0.9298009276390076, 1.1861971616744995, -0.3024958372116089, -0.1503090262413025, -0.02400583028793335, -0.11929035931825638, -0.15742143988609314, 0.48377883434295654, -0.3647904396057129, 0.5628505945205688, -0.11334487795829773, 1.1823221445083618, -0.40515103936195374, 0.721672534942627, -0.10132038593292236, -0.24058079719543457, 0.1002013087272644, 0.19290435314178467, 0.45183271169662476, -0.10542857646942139, 0.6251848340034485, 1.920799732208252, 0.30497118830680847, -0.6016159653663635, -0.06725876033306122, 0.5124351978302002, -0.4898214340209961, 0.6420090794563293, 1.145547866821289, -0.28720903396606445, -0.6665225625038147, -0.5743541717529297, 0.33738595247268677, 0.04394605755805969, -0.17965739965438843, 0.4630800485610962, 1.9549418687820435, 1.499469518661499, -0.26749706268310547, 1.013324499130249, -0.1594688892364502, 1.5651204586029053, -0.15942925214767456, 0.3938906490802765, 1.396590232849121, -0.034020185470581055, 1.266058087348938, 0.31674638390541077, -0.1963104009628296, 1.3712143898010254, -0.16186241805553436, -0.24979910254478455, -0.10034114122390747, 0.6517561078071594, -0.18331456184387207, -0.36358994245529175, -0.5206224918365479, 0.3253186047077179, -0.19119930267333984, -0.3530312776565552, 0.2559228837490082, -0.32011520862579346, -0.07653352618217468, -0.11570292711257935, 0.9453092813491821, -0.27925050258636475, -0.38690024614334106, 1.1902989149093628, -0.19653043150901794, -0.14334934949874878, -0.34923264384269714, -0.15211451053619385, 1.2928017377853394, -0.44817331433296204, -0.179985910654068, 0.3015339970588684, 0.33490699529647827, 1.660330057144165, 0.26083239912986755, -0.18814322352409363, -0.601818859577179, 0.4833199381828308, -0.5184894800186157, 0.6283581256866455, -0.26078107953071594, 0.9463892579078674], [0.739729642868042, -0.12702879309654236, -0.2848263680934906, 0.6780651807785034, -0.35315048694610596, 0.7912313342094421, 0.7396857142448425, 0.45665502548217773, -0.07686340808868408, -0.28985410928726196, 0.8541136980056763, -0.3629511594772339, -0.11183390021324158, -0.18863335251808167, -0.18588191270828247, -0.7700271606445312, 0.20152443647384644, -0.3001876175403595, 1.272338628768921, 0.6204864978790283, 1.5249296426773071, 0.4883478879928589, 1.092951774597168, -0.4454115331172943, -1.0937156677246094, 0.3861891031265259, 0.5429327487945557, 1.3851189613342285, -0.2507876753807068, -0.17371639609336853, -0.3262343406677246, -0.24058040976524353, -0.2925022840499878, -0.1293015033006668, -0.33463194966316223, -0.27496397495269775, 0.39063888788223267, 1.4044265747070312, -0.3735160231590271, -0.18397580087184906, -0.13594649732112885, 0.7741053104400635, -0.28197017312049866, -0.22951865196228027, -0.3001438081264496, -0.23910605907440186, 1.034385323524475, 0.9700469374656677, -0.25552937388420105, 0.6180644035339355, 1.2877644300460815, -0.1851099133491516, 0.7981921434402466, -0.2301802635192871, -0.22153569757938385, 0.7676874399185181, -0.29257306456565857, 0.8624702095985413, -0.30312246084213257, -0.30667585134506226, -0.24988946318626404, 0.8361133337020874, 0.03658130764961243, -0.2741222679615021, -0.29662537574768066, 1.7556848526000977, 0.4119012653827667, 1.5469602346420288, 1.1378703117370605, -0.40455350279808044, -0.12513571977615356, -0.27082300186157227, -0.3255459666252136, 0.0452844500541687, -0.3767146170139313, -0.3091731369495392, -0.5844218730926514, 0.0913371741771698, 0.14801621437072754, 1.2666969299316406, -0.3005925416946411, -0.21734273433685303, 1.0087196826934814, -0.15669190883636475, 0.9223219752311707, -0.3128108084201813, -0.24609725177288055, -0.335518479347229, -0.33807578682899475, -0.18530058860778809, -0.3638553023338318, 0.38131770491600037, -0.14375922083854675, 0.2605685591697693, -0.29118192195892334, -0.3344280421733856, -0.7176907658576965, 1.1615989208221436, 0.5678713321685791, 1.0606110095977783, -0.35263898968696594, -0.11176306009292603, -0.1758536994457245, -0.30536577105522156, -0.06311528384685516, -0.23980242013931274, 0.671806275844574, -0.19663754105567932, 0.07976487278938293, -0.22667694091796875, 1.8176223039627075, 0.2785699963569641, 0.28781062364578247, -0.2637975215911865, 1.6694514751434326, 1.832756757736206, -0.3024958372116089, -0.1503090262413025, -0.39617919921875, -0.11929035931825638, -0.15742143988609314, 0.687868595123291, -0.3647904396057129, 0.5542294979095459, -0.33179301023483276, 0.9881149530410767, -0.20368961989879608, 0.47114408016204834, -0.10132038593292236, -0.23620444536209106, -0.1591738760471344, 0.22360336780548096, -0.031103283166885376, -0.10542857646942139, 0.5009294152259827, 1.1291334629058838, 0.7407937049865723, -0.6016159653663635, 0.6442449688911438, 0.544766366481781, -0.4898214340209961, 0.9687836170196533, 0.8900538682937622, -0.28720903396606445, -0.6665225625038147, -0.5743541717529297, 0.33738595247268677, -0.15538910031318665, -0.17965739965438843, 0.333149254322052, 2.0747859477996826, 1.2204272747039795, 0.24817854166030884, 1.3433773517608643, -0.1594688892364502, 1.432145357131958, -0.10268045216798782, 0.6719772815704346, 1.4293290376663208, -0.2314888834953308, 1.2291076183319092, 0.02233600616455078, -0.1963104009628296, 1.3112742900848389, -0.16186241805553436, -0.24979910254478455, -0.10034114122390747, 0.6812681555747986, 0.41686898469924927, -0.3218507170677185, -0.745795488357544, -0.3158751428127289, 0.8704078197479248, -0.3530312776565552, 0.2559228837490082, 0.10669565200805664, -0.07653352618217468, -0.31222549080848694, 0.6585114002227783, -0.27925050258636475, -0.08783209323883057, 1.659654140472412, -0.4117862284183502, -0.14334934949874878, -0.34923264384269714, -0.5480598211288452, 1.367337703704834, -0.3501039147377014, -0.179985910654068, 0.31230467557907104, 0.33490699529647827, 1.2732079029083252, 1.262858510017395, -0.18814322352409363, -0.601818859577179, 0.10339120030403137, -0.5184894800186157, -0.42077064514160156, -0.26078107953071594, 0.7563056349754333], [1.3047823905944824, -0.12702879309654236, -0.2848263680934906, 0.5449303388595581, -0.35315048694610596, 1.2224234342575073, 0.8191938400268555, 0.7355157136917114, -0.07686340808868408, -0.16823157668113708, 0.6816946864128113, 0.9285929203033447, -0.11183390021324158, -0.18863335251808167, 0.10689869523048401, -0.09743022918701172, -0.2285488247871399, -0.3001876175403595, 1.1712348461151123, 0.4481694996356964, 1.6496375799179077, 0.06680786609649658, 0.9985853433609009, -0.5004634857177734, -1.0538111925125122, 0.33220839500427246, 0.37370234727859497, 1.4270949363708496, -0.39719536900520325, -0.17371639609336853, -0.33406466245651245, -0.24058040976524353, -0.9790478944778442, -0.1293015033006668, -0.33463194966316223, -0.27496397495269775, 0.2582966089248657, 1.3763773441314697, -0.3735160231590271, -0.016274169087409973, -0.13594649732112885, 0.17108601331710815, -0.28197017312049866, -0.22951865196228027, -0.3001438081264496, -0.23910605907440186, 0.8358247876167297, 1.5262136459350586, -0.25552937388420105, 0.5026644468307495, 1.4324051141738892, -0.1851099133491516, 1.4147883653640747, -0.2301802635192871, -0.07235077023506165, 0.7413142919540405, -0.29257306456565857, 1.4718313217163086, -0.30312246084213257, -0.30667585134506226, -0.24988946318626404, 0.8123152256011963, 0.8812047243118286, -0.2741222679615021, -0.29662537574768066, 2.0630524158477783, 0.46238914132118225, 1.813033938407898, 1.355806827545166, -0.40455350279808044, 0.5190227031707764, -0.27082300186157227, -0.3255459666252136, -0.2921525835990906, -0.3767146170139313, -0.3091731369495392, -0.7182999849319458, 0.03680217266082764, -0.21875137090682983, 1.9389030933380127, -0.3005925416946411, -0.21734273433685303, 0.9245821237564087, -0.3638487756252289, 1.3678174018859863, -0.3128108084201813, -0.05823037028312683, -0.335518479347229, -0.33807578682899475, -0.014587625861167908, -0.3638553023338318, 0.1839241087436676, -0.14375922083854675, 0.43708449602127075, -0.4431609809398651, -0.3344280421733856, -0.7176907658576965, 0.5324409008026123, 0.8357352614402771, 1.5372521877288818, -0.35263898968696594, -0.11176306009292603, -0.1758536994457245, -0.30536577105522156, -0.06311528384685516, -0.23980242013931274, 0.44175243377685547, -0.19663754105567932, -0.2404516339302063, -0.22667694091796875, 1.2318673133850098, 0.2785699963569641, 0.9908298850059509, -0.2637975215911865, 2.0684266090393066, 1.2411588430404663, -0.3024958372116089, -0.1503090262413025, -0.39617919921875, -0.11929035931825638, -0.15742143988609314, 0.8612545728683472, -0.3647904396057129, 1.28183114528656, -0.35213643312454224, 0.46153736114501953, -0.1569424569606781, 1.3265745639801025, -0.10132038593292236, 0.05268675088882446, -0.2254386842250824, 0.31145310401916504, -0.11580690741539001, -0.10542857646942139, 0.6092341542243958, 1.1374647617340088, 1.1365894079208374, -0.6016159653663635, 0.7784105539321899, 0.8302444815635681, -0.4898214340209961, 1.3170268535614014, 0.4280044734477997, -0.28720903396606445, -0.6665225625038147, -0.5743541717529297, 0.33738595247268677, 0.5721175670623779, -0.17965739965438843, -0.2543191909790039, 1.718024492263794, 1.856873631477356, 0.24886322021484375, -0.4157399535179138, -0.1594688892364502, 1.7017898559570312, -0.15942925214767456, 0.9824577569961548, 0.8557338714599609, -0.2314888834953308, 0.4195936918258667, 0.10478463768959045, -0.1963104009628296, 0.9458836913108826, -0.16186241805553436, -0.24979910254478455, -0.10034114122390747, 1.0357458591461182, 0.10184511542320251, -0.2588321566581726, -0.6444576978683472, -0.08113044500350952, 0.7483657598495483, -0.3530312776565552, 0.15372800827026367, -0.9224947690963745, 0.21670091152191162, -0.31222549080848694, 1.4122459888458252, -0.27925050258636475, -0.08103615045547485, 1.4369992017745972, -0.4458828568458557, -0.14334934949874878, -0.34923264384269714, -1.1235157251358032, 1.2233744859695435, -0.44817331433296204, -0.179985910654068, -0.11431479454040527, 0.33490699529647827, 1.1510378122329712, 1.5736509561538696, -0.18814322352409363, -0.601818859577179, 0.45259028673171997, -0.5184894800186157, -0.16660240292549133, -0.26078107953071594, 1.0692720413208008], [0.8816569447517395, -0.12702879309654236, -0.2848263680934906, 0.7026299238204956, -0.35315048694610596, 0.9702447056770325, 0.3936086893081665, 0.4281538128852844, -0.006190501153469086, 0.524574875831604, 0.3960839509963989, 1.6006768941879272, -0.11183390021324158, -0.18863335251808167, 0.3379955589771271, -0.7507317066192627, -0.2285488247871399, -0.3001876175403595, 1.0503180027008057, 0.8414881229400635, 0.8824701309204102, 0.046001553535461426, 0.8948284387588501, -0.5004634857177734, -1.315035343170166, 0.42480528354644775, 0.46651220321655273, 1.2189886569976807, -0.13698992133140564, -0.17371639609336853, -0.4127652049064636, -0.24058040976524353, -0.9790478944778442, -0.1293015033006668, 0.10225939750671387, -0.17754513025283813, -0.02319943904876709, 1.8186900615692139, -0.3735160231590271, -0.18397580087184906, 0.19943495094776154, 0.6441454887390137, -0.28197017312049866, -0.22951865196228027, -0.3001438081264496, -0.23910605907440186, 0.7927079796791077, 0.6346583366394043, -0.25552937388420105, 0.41210684180259705, 1.3835251331329346, -0.1851099133491516, 0.5463550686836243, -0.2301802635192871, -0.28901156783103943, 0.742882251739502, -0.29257306456565857, 0.5034266114234924, -0.30312246084213257, -0.30667585134506226, -0.24988946318626404, 0.9691059589385986, 1.1467101573944092, -0.2741222679615021, -0.29662537574768066, 2.012824296951294, 1.0555989742279053, 1.068919062614441, 1.0631928443908691, -0.40455350279808044, -0.1885530948638916, -0.27082300186157227, -0.22954219579696655, 0.5442833304405212, -0.3767146170139313, -0.3091731369495392, -0.7182999849319458, 0.06191760301589966, -0.21875137090682983, 1.783200979232788, -0.3005925416946411, -0.21734273433685303, 1.8208343982696533, -0.2982141077518463, 1.2777612209320068, -0.3128108084201813, -0.24609725177288055, -0.335518479347229, -0.33807578682899475, -0.016142889857292175, -0.3638553023338318, -0.35621964931488037, -0.14375922083854675, 0.8019250631332397, -0.4431609809398651, -0.3344280421733856, -0.7176907658576965, 0.6790660619735718, 0.43038928508758545, 0.6427565217018127, -0.35263898968696594, -0.11176306009292603, -0.1758536994457245, -0.30536577105522156, -0.06311528384685516, -0.23980242013931274, 1.380511999130249, -0.19663754105567932, -0.2404516339302063, -0.22667694091796875, 1.7561370134353638, 0.2785699963569641, 0.6720152497291565, -0.2637975215911865, 1.7633073329925537, 1.968043565750122, -0.3024958372116089, -0.1503090262413025, 0.28933632373809814, -0.11929035931825638, -0.15742143988609314, 1.169706106185913, -0.3647904396057129, 0.8444415330886841, -0.5946764349937439, 0.6699284315109253, 0.14407357573509216, 1.4295247793197632, -0.10132038593292236, -0.213359534740448, -0.1803971379995346, 0.18148058652877808, 0.31672948598861694, -0.10542857646942139, 0.3367941975593567, 1.43721604347229, 0.9887261390686035, -0.6016159653663635, 0.5754079818725586, 0.6775103211402893, -0.4898214340209961, 0.5575020909309387, 1.4687983989715576, -0.28720903396606445, -0.6665225625038147, -0.5743541717529297, 0.33738595247268677, 0.6283799409866333, -0.17965739965438843, 0.4910159707069397, 2.355660915374756, 2.6537303924560547, -0.1973625272512436, -0.40930604934692383, -0.1594688892364502, 1.6099345684051514, 0.6991875171661377, 0.3710460364818573, 0.8600267171859741, -0.2314888834953308, 1.2894457578659058, 0.41050592064857483, -0.1963104009628296, 1.740739345550537, -0.16186241805553436, -0.24979910254478455, -0.10034114122390747, 0.4498313069343567, 0.27730756998062134, 0.014145046472549438, -0.745795488357544, -0.07899317145347595, 0.8082319498062134, -0.3530312776565552, 0.2559228837490082, -0.9224947690963745, -0.07653352618217468, -0.31222549080848694, 0.48386824131011963, -0.27925050258636475, -0.19348496198654175, 1.229567527770996, -0.48901817202568054, -0.14334934949874878, -0.34923264384269714, -1.1804910898208618, 1.2302356958389282, -0.44817331433296204, -0.179985910654068, -0.6007946729660034, 0.33490699529647827, 2.1196486949920654, 1.1512573957443237, -0.18814322352409363, -0.601818859577179, 0.5254021286964417, -0.5184894800186157, -0.19630923867225647, -0.26078107953071594, 0.7559310793876648], [1.4301261901855469, -0.12702879309654236, -0.2848263680934906, 1.352339744567871, -0.35315048694610596, 1.335372805595398, 0.17587053775787354, 0.5133408904075623, 0.7897030115127563, -0.1683485507965088, 1.1650867462158203, 0.9012078046798706, -0.11183390021324158, -0.18863335251808167, 0.3409147560596466, -0.8824635744094849, -0.2285488247871399, -0.3001876175403595, 1.5117714405059814, 1.7141419649124146, 1.2893636226654053, -0.35008952021598816, 1.424888253211975, -0.5004634857177734, -2.089597463607788, -0.18703484535217285, 0.24782639741897583, 0.9789190888404846, -0.39719536900520325, -0.17371639609336853, -0.4588732123374939, -0.24058040976524353, -0.9790478944778442, -0.1293015033006668, -0.33463194966316223, -0.27496397495269775, -0.3081934452056885, 0.9020416140556335, -0.3735160231590271, -0.18397580087184906, -0.13594649732112885, 1.4352946281433105, -0.28197017312049866, -0.22951865196228027, -0.3001438081264496, -0.23910605907440186, 0.40695035457611084, 0.5648372173309326, -0.25552937388420105, 0.6962906122207642, 1.278825044631958, -0.1851099133491516, 1.757490873336792, -0.2301802635192871, -0.28901156783103943, 0.6839389801025391, -0.29257306456565857, 0.9027270674705505, -0.30312246084213257, -0.30667585134506226, -0.24988946318626404, 0.8308711051940918, 0.6156514883041382, -0.2741222679615021, -0.29662537574768066, 2.3461010456085205, 1.728885531425476, 1.0203977823257446, 1.5643525123596191, -0.40455350279808044, -0.21793079376220703, -0.27082300186157227, -0.26457715034484863, -0.20898084342479706, -0.3767146170139313, -0.3091731369495392, -0.7182999849319458, 0.31213364005088806, -0.21875137090682983, 2.375640869140625, -0.3005925416946411, -0.21734273433685303, 0.8226083517074585, -0.3638487756252289, 0.35203272104263306, -0.3128108084201813, -0.24609725177288055, -0.335518479347229, -0.33807578682899475, 1.1537120342254639, -0.3638553023338318, -0.22073359787464142, -0.14375922083854675, 0.9420349597930908, -0.04487946629524231, -0.3344280421733856, -0.7176907658576965, 1.7239257097244263, 0.35964566469192505, 0.679793119430542, -0.35263898968696594, -0.11176306009292603, -0.1758536994457245, -0.30536577105522156, -0.06311528384685516, -0.23980242013931274, 0.6394711136817932, -0.19663754105567932, -0.2404516339302063, -0.22667694091796875, 1.8542793989181519, 0.2785699963569641, -0.05648261308670044, -0.2637975215911865, 2.3337295055389404, 2.292429208755493, -0.3024958372116089, -0.1503090262413025, 0.49790769815444946, -0.11929035931825638, -0.15742143988609314, 1.1920205354690552, -0.3647904396057129, -0.019251346588134766, -0.5946764349937439, 1.2121695280075073, 0.725420355796814, 1.5352288484573364, -0.10132038593292236, -0.08459144830703735, -0.39191633462905884, -0.1413777768611908, 0.8020501136779785, -0.10542857646942139, 0.6989628672599792, 1.1154327392578125, 1.1907641887664795, -0.6016159653663635, 1.6054918766021729, 0.7303540110588074, -0.4898214340209961, 0.9970798492431641, 0.8917148113250732, -0.28720903396606445, -0.6665225625038147, -0.5743541717529297, 0.33738595247268677, 0.18800878524780273, -0.17965739965438843, 0.2595069408416748, 1.4267934560775757, 2.615293502807617, 0.2631368041038513, -0.6309402585029602, -0.1594688892364502, 2.1293985843658447, 0.8957694172859192, 0.31263622641563416, 0.09389513731002808, -0.2314888834953308, 1.150471568107605, 0.36014434695243835, -0.1963104009628296, 0.9216805100440979, -0.16186241805553436, -0.24979910254478455, -0.10034114122390747, -0.21935367584228516, 0.7065059542655945, 0.9141653180122375, -0.745795488357544, -0.3158751428127289, 1.2363011837005615, -0.3530312776565552, 0.2559228837490082, -0.9224947690963745, -0.07653352618217468, -0.31222549080848694, 0.3101646900177002, -0.27925050258636475, -0.553607165813446, 0.6545806527137756, -0.48901817202568054, -0.08730434626340866, -0.34923264384269714, -1.1804910898208618, 1.061995029449463, -0.44817331433296204, -0.179985910654068, -0.6007946729660034, 0.33490699529647827, 1.2724223136901855, 1.9710760116577148, -0.18814322352409363, -0.601818859577179, 0.7210021018981934, -0.5184894800186157, -0.42077064514160156, -0.26078107953071594, 1.5689043998718262], [0.8797929883003235, -0.12702879309654236, -0.2848263680934906, 1.5631330013275146, -0.35315048694610596, 1.0297503471374512, 0.376389741897583, 0.9192479848861694, -0.07686340808868408, 0.42734551429748535, 0.788802981376648, 2.1163864135742188, -0.11183390021324158, -0.18863335251808167, 0.5329009294509888, 0.2719360589981079, -0.2285488247871399, -0.3001876175403595, 1.4872627258300781, 0.8411757946014404, 1.0321730375289917, 0.3027130365371704, 0.9515029191970825, -0.5004634857177734, -1.6725339889526367, 0.622674822807312, 0.5429327487945557, 1.6196942329406738, -0.39719536900520325, -0.17371639609336853, -0.4588732123374939, -0.24058040976524353, -0.9790478944778442, -0.1293015033006668, -0.017064034938812256, -0.27496397495269775, -0.18502457439899445, 1.618976354598999, 0.2926550507545471, -0.18397580087184906, 0.3507280945777893, 0.7608391046524048, -0.28197017312049866, -0.22951865196228027, -0.3001438081264496, -0.23910605907440186, 1.004753828048706, 1.2513549327850342, -0.25552937388420105, 0.6732124090194702, 1.9340521097183228, -0.1851099133491516, 1.7680931091308594, -0.2301802635192871, -0.231901153922081, 1.3259894847869873, -0.29257306456565857, 1.3027217388153076, -0.30312246084213257, -0.30667585134506226, -0.24988946318626404, 1.0861009359359741, 1.2046763896942139, -0.2741222679615021, -0.29662537574768066, 2.034911632537842, 1.7928342819213867, 1.4886144399642944, 1.025015115737915, -0.40455350279808044, -0.28047192096710205, -0.27082300186157227, -0.3255459666252136, 0.3742000460624695, -0.3767146170139313, -0.3091731369495392, -0.7182999849319458, -0.3013615906238556, -0.21875137090682983, 2.3389570713043213, -0.3005925416946411, -0.21734273433685303, 1.4322577714920044, 0.0662568211555481, 1.7679848670959473, -0.3128108084201813, -0.24609725177288055, -0.335518479347229, -0.33807578682899475, 0.5564945936203003, -0.3638553023338318, -0.11766812205314636, -0.14375922083854675, 0.7430955171585083, -0.4431609809398651, -0.3344280421733856, -0.7176907658576965, 0.9878940582275391, 0.7723386883735657, 1.2679367065429688, -0.35263898968696594, -0.11176306009292603, -0.1758536994457245, -0.30536577105522156, -0.06311528384685516, -0.23980242013931274, 0.670953094959259, 0.08857595920562744, -0.2404516339302063, -0.22667694091796875, 1.757637619972229, 0.2785699963569641, 1.0126559734344482, -0.2637975215911865, 2.0890824794769287, 2.3553919792175293, -0.3024958372116089, -0.1503090262413025, -0.39617919921875, -0.11929035931825638, -0.15742143988609314, 1.3935911655426025, -0.3647904396057129, 0.9976801872253418, 0.22938406467437744, 0.3702728748321533, 0.56123948097229, 2.6608381271362305, -0.10132038593292236, -0.111194908618927, -0.39191633462905884, -0.21739104390144348, 0.5342462658882141, -0.10542857646942139, 0.16712278127670288, 1.8232920169830322, 1.9423683881759644, -0.6016159653663635, 1.1027295589447021, 1.0209109783172607, -0.4898214340209961, 1.4373983144760132, 1.264084815979004, -0.28720903396606445, -0.6665225625038147, -0.5743541717529297, 0.33738595247268677, 1.5064154863357544, -0.17965739965438843, -0.07423901557922363, 1.9171143770217896, 2.9848146438598633, -0.26749706268310547, -0.6309402585029602, -0.1594688892364502, 2.371467351913452, 1.2080252170562744, 0.4420528709888458, 1.0892101526260376, -0.2314888834953308, 1.6903740167617798, 0.4079742729663849, -0.1963104009628296, 1.749086856842041, -0.16186241805553436, -0.24979910254478455, -0.10034114122390747, 0.6930995583534241, 0.2976205348968506, 0.34972327947616577, -0.745795488357544, -0.2523302733898163, 1.2366517782211304, -0.3530312776565552, 0.2559228837490082, -0.9224947690963745, -0.07653352618217468, -0.31222549080848694, 0.8261096477508545, -0.27925050258636475, 0.14504122734069824, 1.5269311666488647, -0.48901817202568054, -0.14334934949874878, -0.34923264384269714, -1.1804910898208618, 1.9002219438552856, -0.44817331433296204, -0.179985910654068, -0.6007946729660034, 0.33490699529647827, 1.875324010848999, 1.7979445457458496, -0.18814322352409363, -0.601818859577179, 1.1026930809020996, -0.5184894800186157, -0.15464463829994202, -0.26078107953071594, 1.1999056339263916], [0.6600614786148071, -0.12702879309654236, -0.2848263680934906, 1.0962626934051514, -0.35315048694610596, 1.2972568273544312, -0.2574056386947632, 0.4367460608482361, 0.3047255873680115, 0.6442252993583679, 0.07679963111877441, 1.0990355014801025, -0.11183390021324158, -0.18863335251808167, 0.5372610092163086, -0.3470849394798279, -0.2285488247871399, -0.3001876175403595, 2.100425958633423, 1.1160528659820557, 1.0056543350219727, 0.18655508756637573, 1.3666819334030151, -0.5004634857177734, -1.1573470830917358, 0.7908453941345215, 0.5429327487945557, 1.2908592224121094, -0.39719536900520325, -0.17371639609336853, -0.3963606357574463, -0.24058040976524353, -0.9790478944778442, -0.1293015033006668, -0.33463194966316223, -0.27496397495269775, 0.25829601287841797, 1.5472028255462646, -0.3735160231590271, -0.18397580087184906, -0.13594649732112885, 0.4440368413925171, -0.28197017312049866, -0.22951865196228027, -0.3001438081264496, -0.23910605907440186, 0.8213917016983032, 0.5492514371871948, -0.25552937388420105, 0.7197036743164062, 1.630987286567688, -0.1851099133491516, 1.2751970291137695, -0.2301802635192871, -0.16745179891586304, 1.441833257675171, -0.29257306456565857, 0.6626583933830261, -0.30312246084213257, -0.30667585134506226, -0.24988946318626404, 1.2115663290023804, 0.40609991550445557, -0.2741222679615021, -0.29662537574768066, 1.7160460948944092, 1.1607304811477661, 1.1002143621444702, 1.0375819206237793, -0.40455350279808044, 0.1165463924407959, -0.27082300186157227, -0.3033173680305481, 0.9921514391899109, -0.3767146170139313, -0.3091731369495392, -0.7182999849319458, 0.10397738218307495, -0.21875137090682983, 1.5412006378173828, -0.3005925416946411, -0.21734273433685303, 1.770254135131836, 0.08603662252426147, 0.7011033892631531, -0.3128108084201813, -0.24609725177288055, -0.335518479347229, -0.33807578682899475, 0.7570000290870667, -0.2650463581085205, -0.05596625804901123, -0.14375922083854675, 0.49053674936294556, -0.4431609809398651, -0.3344280421733856, -0.7176907658576965, 0.4903583228588104, 0.4284495711326599, 0.5302630662918091, -0.35263898968696594, -0.11176306009292603, -0.1758536994457245, -0.30536577105522156, -0.06311528384685516, -0.23980242013931274, -0.17878802120685577, -0.19663754105567932, -0.2404516339302063, -0.22667694091796875, 2.6150856018066406, 0.2785699963569641, 0.3100178837776184, -0.2637975215911865, 1.5606095790863037, 1.8270082473754883, -0.3024958372116089, -0.1503090262413025, -0.3466752767562866, -0.11929035931825638, -0.15742143988609314, 0.6652019023895264, -0.3647904396057129, 0.9652615785598755, -0.3046436607837677, 1.097318410873413, -0.40515103936195374, 1.2754420042037964, -0.10132038593292236, -0.009809792041778564, -0.39191633462905884, 0.6776095032691956, 0.7770636081695557, -0.10542857646942139, 0.7398287653923035, 1.3278594017028809, 1.0338072776794434, -0.6016159653663635, 0.5096417665481567, 0.9572210907936096, -0.4898214340209961, 0.6969430446624756, 2.2625114917755127, -0.28720903396606445, -0.6665225625038147, -0.5743541717529297, 0.33738595247268677, 0.21082523465156555, -0.17965739965438843, 1.1117842197418213, 2.262416124343872, 1.7752248048782349, -0.26749706268310547, 0.029524922370910645, -0.1594688892364502, 2.4103095531463623, 1.1893627643585205, 0.6671472787857056, 1.3938570022583008, -0.2314888834953308, 1.2791606187820435, 0.1647556722164154, -0.1963104009628296, 2.2433907985687256, -0.16186241805553436, -0.24979910254478455, 0.06137968599796295, 1.0600993633270264, 0.39283692836761475, -0.36358994245529175, -0.745795488357544, -0.3158751428127289, 0.7773773670196533, -0.3530312776565552, 0.2559228837490082, -0.9224947690963745, -0.07653352618217468, -0.31222549080848694, 0.26212048530578613, -0.27925050258636475, -0.5877312421798706, 1.143621563911438, -0.48901817202568054, -0.14334934949874878, -0.34923264384269714, -1.1804910898208618, 1.3725712299346924, -0.44817331433296204, -0.179985910654068, -0.6007946729660034, 0.33490699529647827, 2.510810375213623, 0.924551248550415, -0.18814322352409363, -0.601818859577179, 0.6629990935325623, -0.5184894800186157, 0.1100662350654602, -0.26078107953071594, 1.6748785972595215], [2.0519907474517822, -0.12702879309654236, -0.2848263680934906, 2.1410350799560547, -0.35315048694610596, 1.7944858074188232, 0.5531579852104187, -0.07476773858070374, 1.2196507453918457, -0.28985410928726196, 1.1092957258224487, 1.3425546884536743, -0.11183390021324158, -0.18863335251808167, 0.02103021740913391, -0.8466793298721313, -0.2285488247871399, -0.3001876175403595, 1.6078557968139648, 1.2263048887252808, 1.8455246686935425, -0.35960090160369873, 1.149487853050232, -0.5004634857177734, -2.077425956726074, 0.35905253887176514, 0.08453968167304993, 1.79252290725708, -0.39719536900520325, -0.17371639609336853, -0.4588732123374939, -0.24058040976524353, -0.9790478944778442, -0.1293015033006668, -0.33463194966316223, -0.27496397495269775, -0.34865689277648926, 1.6241874694824219, 0.14149540662765503, -0.18397580087184906, 0.36060941219329834, 1.158328890800476, -0.28197017312049866, -0.22951865196228027, -0.3001438081264496, -0.23910605907440186, 1.620141863822937, 1.3411753177642822, -0.25552937388420105, 1.030893325805664, 2.1961917877197266, -0.1851099133491516, 2.233837604522705, -0.2301802635192871, -0.28901156783103943, 1.6039047241210938, -0.29257306456565857, 1.4858157634735107, -0.30312246084213257, -0.30667585134506226, -0.24988946318626404, 0.9111533164978027, 0.8229655027389526, -0.2741222679615021, -0.29662537574768066, 2.9948136806488037, 2.230516195297241, 1.9742950201034546, 2.3271617889404297, -0.40455350279808044, 0.2915074825286865, -0.27082300186157227, -0.3255459666252136, 0.501922607421875, -0.3767146170139313, -0.3091731369495392, -0.7182999849319458, -0.3013615906238556, -0.21875137090682983, 2.556889295578003, -0.3005925416946411, -0.15899626910686493, 1.3700281381607056, -0.0024015307426452637, 1.0229811668395996, -0.3128108084201813, -0.24609725177288055, -0.335518479347229, -0.33807578682899475, 1.7966598272323608, -0.3638553023338318, 0.26206979155540466, -0.14375922083854675, 0.20231211185455322, -0.4431609809398651, -0.3344280421733856, -0.7176907658576965, 1.3654035329818726, 1.2002792358398438, 1.5672030448913574, -0.35263898968696594, -0.11176306009292603, -0.1758536994457245, -0.30536577105522156, -0.06311528384685516, -0.23980242013931274, 0.25179994106292725, -0.18307721614837646, -0.2404516339302063, -0.22667694091796875, 2.4185638427734375, 0.2785699963569641, 0.6804353594779968, -0.2637975215911865, 2.538404941558838, 2.307936191558838, -0.3024958372116089, -0.1503090262413025, -0.3433045446872711, -0.11929035931825638, -0.15742143988609314, 1.6404845714569092, -0.3647904396057129, 0.2123906910419464, -0.4849720001220703, 1.2257269620895386, -0.010185778141021729, 1.7290407419204712, -0.10132038593292236, -0.4877116084098816, -0.39191633462905884, 0.09408837556838989, 1.134548544883728, -0.10542857646942139, 1.2156343460083008, 1.2982935905456543, 1.8433767557144165, -0.6016159653663635, 1.4162776470184326, 0.9610547423362732, -0.4898214340209961, 1.6269843578338623, 1.3222651481628418, -0.28720903396606445, -0.6665225625038147, -0.5743541717529297, 0.33738595247268677, 1.1695290803909302, -0.17965739965438843, 0.2574648857116699, 1.8389278650283813, 2.584947109222412, -0.1230199933052063, -0.06087523698806763, -0.1594688892364502, 2.2529478073120117, 1.5823967456817627, 0.8778969049453735, 1.1697756052017212, -0.2314888834953308, 1.7831717729568481, -0.34454429149627686, -0.1963104009628296, 1.7101953029632568, -0.16186241805553436, -0.24979910254478455, 0.3684691786766052, 0.3240751624107361, 1.0284414291381836, 0.12821221351623535, -0.745795488357544, -0.3158751428127289, 1.5162347555160522, -0.3530312776565552, 0.2559228837490082, -0.9224947690963745, 0.5275671482086182, -0.31222549080848694, 0.2472316026687622, -0.27925050258636475, -0.5877312421798706, 1.6998910903930664, -0.48901817202568054, -0.14334934949874878, -0.34923264384269714, -1.1804910898208618, 2.467966079711914, -0.44817331433296204, -0.179985910654068, -0.6007946729660034, 0.33490699529647827, 2.099031925201416, 2.1072158813476562, -0.18814322352409363, -0.601818859577179, 0.486828088760376, -0.5184894800186157, -0.42077064514160156, -0.26078107953071594, 1.3504595756530762]], "musicnn_tags1": ["rock", "pop", "alternative", "indie", "electronic", "female vocalists", "dance", "00s", "alternative rock", "jazz", "beautiful", "metal", "chillout", "male vocalists", "classic rock", "soul", "indie rock", "Mellow", "electronica", "80s", "folk", "90s", "chill", "instrumental", "punk", "oldies", "blues", "hard rock", "ambient", "acoustic", "experimental", "female vocalist", "guitar", "Hip-Hop", "70s", "party", "country", "easy listening", "sexy", "catchy", "funk", "electro", "heavy metal", "Progressive rock", "60s", "rnb", "indie pop", "sad", "House", "happy"]}